curefit/__init__.py
curefit/curefit_linreg.py
curefit/unc_calc.py
curefit-0.2.0.dist-info/LICENSE
curefit-0.2.0.dist-info/WHEEL
curefit-0.2.0.dist-info/METADATA
curefit-0.2.0.dist-info/RECORD
