Metadata-Version: 2.1
Name: curefit
Version: 0.2.0
Summary: Linear regression of data sets with correlated and uncorrelated uncertainties.
Author-email: Reto Trappitsch <reto@galactic-forensics.space>
Requires-Python: >=3.8
Classifier: Development Status :: 5 - Production/Stable
Classifier: Programming Language :: Python
Classifier: Programming Language :: Python :: 3.8
Classifier: Programming Language :: Python :: 3.9
Classifier: Programming Language :: Python :: 3.10
Classifier: Programming Language :: Python :: 3.11
Classifier: Operating System :: OS Independent
Classifier: License :: OSI Approved :: MIT License
Classifier: Intended Audience :: Science/Research
Classifier: Topic :: Scientific/Engineering
Classifier: Topic :: Scientific/Engineering :: Physics
Requires-Dist: numpy
Requires-Dist: scipy
Requires-Dist: nox ; extra == "dev"
Requires-Dist: darglint>=1.5.1 ; extra == "test"
Requires-Dist: flake8>=4,<5 ; extra == "test"
Requires-Dist: flake8-bandit ; extra == "test"
Requires-Dist: flake8-black ; extra == "test"
Requires-Dist: flake8-bugbear ; extra == "test"
Requires-Dist: flake8-docstrings ; extra == "test"
Requires-Dist: flake8-import-order ; extra == "test"
Requires-Dist: bandit<=1.7.2 ; extra == "test"
Requires-Dist: pytest>=6.0 ; extra == "test"
Requires-Dist: pytest-cov ; extra == "test"
Project-URL: Home, https://github.com/galactic-forensics/CUREFit
Provides-Extra: dev
Provides-Extra: test
